ninethreesix/COMMON.TXT
ninethreesix/__init__.py
ninethreesix/password.py
ninethreesix/test_password.py
ninethreesix/__pycache__/__init__.cpython-310.pyc
ninethreesix/__pycache__/__init__.cpython-314.pyc
ninethreesix/__pycache__/password.cpython-310.pyc
ninethreesix/__pycache__/password.cpython-314.pyc
ninethreesix/__pycache__/test_password.cpython-310-pytest-9.0.2.pyc
ninethreesix/__pycache__/test_password.cpython-314-pytest-9.0.2.pyc
python_ninethreesix-0.3.0.dist-info/licenses/LICENSE.txt
python_ninethreesix-0.3.0.dist-info/METADATA
python_ninethreesix-0.3.0.dist-info/WHEEL
python_ninethreesix-0.3.0.dist-info/entry_points.txt
python_ninethreesix-0.3.0.dist-info/top_level.txt
python_ninethreesix-0.3.0.dist-info/RECORD
