Metadata-Version: 2.4
Name: python-ninethreesix
Version: 0.3.0
Summary: A password generator based on xkcd.com/936
Author-email: Brad Montgomery <brad@bradmontgomery.nte>
License: MIT
Project-URL: Homepage, https://github.com/bradmontgomery/python-ninethreesix
Project-URL: Bug Tracker, https://github.com/bradmontgomery/python-ninethreesix/issues
Keywords: password,utility
Classifier: Development Status :: 4 - Beta
Classifier: Intended Audience :: Developers
Classifier: Intended Audience :: Information Technology
Classifier: Intended Audience :: System Administrators
Classifier: License :: OSI Approved :: MIT License
Classifier: Operating System :: OS Independent
Classifier: Programming Language :: Python
Classifier: Programming Language :: Python :: 3
Classifier: Programming Language :: Python :: 3.12
Classifier: Programming Language :: Python :: 3.13
Classifier: Programming Language :: Python :: 3.14
Classifier: Topic :: Security
Classifier: Topic :: Software Development :: Libraries :: Python Modules
Classifier: Topic :: Utilities
Requires-Python: >=3.12
License-File: LICENSE.txt
Requires-Dist: rich>=13.8.1
Requires-Dist: rich-click>=1.8.9
Dynamic: license-file
